natmeeg-1.6.10.dist-info/licenses/LICENSE
pyeeg/__init__.py
pyeeg/cca.py
pyeeg/connectivity.py
pyeeg/gammatone.py
pyeeg/io.py
pyeeg/mcca.py
pyeeg/models.py
pyeeg/preprocess.py
pyeeg/ratemap.py
pyeeg/simulate.py
pyeeg/utils.py
pyeeg/version.py
pyeeg/vizu.py
pyeeg/bin/__init__.py
pyeeg/bin/gammatone_c.cpython-312-darwin.so
pyeeg/bin/gammatone_c.dll
pyeeg/bin/makeRateMap_c.cpython-312-darwin.so
pyeeg/bin/makeRateMap_c.dll
pyeeg/gammatone_c/gammatone_c.c
pyeeg/gammatone_c/makeRateMap_c.c
natmeeg-1.6.10.dist-info/METADATA
natmeeg-1.6.10.dist-info/WHEEL
natmeeg-1.6.10.dist-info/top_level.txt
natmeeg-1.6.10.dist-info/RECORD
