Metadata-Version: 2.4
Name: natmeeg
Version: 1.6.10
Summary: A library to process M/EEG data with a set of utility functions with a framework focused on continuous recordings and naturalistic stimuli.
Author-email: Hugo Weissbart <hugo.weissbart@donders.ru.nl>
License-Expression: GPL-3.0-or-later
Project-URL: Homepage, https://github.com/Hugo-W/pyEEG
Project-URL: Documentation, https://hugo-w.github.io/pyEEG-docs/
Project-URL: Repository, https://github.com/Hugo-W/pyEEG
Project-URL: Issues, https://github.com/Hugo-W/pyEEG/issues
Keywords: EEG,neuroscience,signal processing
Classifier: Programming Language :: Python :: 3
Classifier: Operating System :: POSIX :: Linux
Classifier: Operating System :: Microsoft :: Windows
Classifier: Operating System :: MacOS
Classifier: Development Status :: 4 - Beta
Classifier: Intended Audience :: Science/Research
Requires-Python: >=3.10
License-File: LICENSE
Requires-Dist: numpy>=1.21.0
Requires-Dist: scipy>=1.7.0
Requires-Dist: scikit-learn>=1.0.0
Requires-Dist: pandas>=1.3.0
Requires-Dist: matplotlib>=3.4.0
Requires-Dist: h5py>=3.3.0
Requires-Dist: psutil>=5.8.0
Requires-Dist: tqdm>=4.62.0
Provides-Extra: mne
Requires-Dist: mne; extra == "mne"
Provides-Extra: docs
Requires-Dist: sphinx; extra == "docs"
Requires-Dist: sphinx-rtd-theme; extra == "docs"
Requires-Dist: nbsphinx; extra == "docs"
Provides-Extra: full
Requires-Dist: mne; extra == "full"
Requires-Dist: sphinx; extra == "full"
Requires-Dist: sphinx-rtd-theme; extra == "full"
Requires-Dist: nbsphinx; extra == "full"
Dynamic: license-file
